llmcompressor/__init__.py
llmcompressor/logger.py
llmcompressor/sentinel.py
llmcompressor/typing.py
llmcompressor/version.py
llmcompressor/args/README.md
llmcompressor/args/__init__.py
llmcompressor/args/dataset_arguments.py
llmcompressor/args/model_arguments.py
llmcompressor/args/recipe_arguments.py
llmcompressor/args/utils.py
llmcompressor/core/__init__.py
llmcompressor/core/helpers.py
llmcompressor/core/lifecycle.py
llmcompressor/core/model_layer.py
llmcompressor/core/session.py
llmcompressor/core/session_functions.py
llmcompressor/core/state.py
llmcompressor/core/events/__init__.py
llmcompressor/core/events/event.py
llmcompressor/datasets/__init__.py
llmcompressor/datasets/utils.py
llmcompressor/entrypoints/README.md
llmcompressor/entrypoints/__init__.py
llmcompressor/entrypoints/oneshot.py
llmcompressor/entrypoints/utils.py
llmcompressor/entrypoints/model_free/README.md
llmcompressor/entrypoints/model_free/__init__.py
llmcompressor/entrypoints/model_free/helpers.py
llmcompressor/entrypoints/model_free/lifecycle.py
llmcompressor/entrypoints/model_free/microscale.py
llmcompressor/entrypoints/model_free/model_utils.py
llmcompressor/entrypoints/model_free/process.py
llmcompressor/entrypoints/model_free/reindex_fused_weights.py
llmcompressor/entrypoints/model_free/save_utils.py
llmcompressor/entrypoints/model_free/validate.py
llmcompressor/metrics/__init__.py
llmcompressor/metrics/logger.py
llmcompressor/metrics/utils/__init__.py
llmcompressor/metrics/utils/frequency_manager.py
llmcompressor/modeling/__init__.py
llmcompressor/modeling/deepseek_v3.py
llmcompressor/modeling/fuse.py
llmcompressor/modeling/granite4.py
llmcompressor/modeling/llama4.py
llmcompressor/modeling/moe_context.py
llmcompressor/modeling/qwen3_moe.py
llmcompressor/modeling/qwen3_next_moe.py
llmcompressor/modeling/qwen3_vl_moe.py
llmcompressor/modifiers/README.md
llmcompressor/modifiers/__init__.py
llmcompressor/modifiers/factory.py
llmcompressor/modifiers/interface.py
llmcompressor-0.9.0.1.dist-info/licenses/LICENSE
llmcompressor-0.9.0.1.dist-info/licenses/NOTICE
llmcompressor-0.9.0.1.dist-info/METADATA
llmcompressor-0.9.0.1.dist-info/WHEEL
llmcompressor-0.9.0.1.dist-info/entry_points.txt
llmcompressor-0.9.0.1.dist-info/top_level.txt
llmcompressor-0.9.0.1.dist-info/RECORD
