Metadata-Version: 2.4
Name: llmcompressor
Version: 0.9.0.1
Summary: A library for compressing large language models utilizing the latest techniques and research in the field for both training aware and post training techniques. The library is designed to be flexible and easy to use on top of PyTorch and HuggingFace Transformers, allowing for quick experimentation.
Home-page: https://github.com/vllm-project/llm-compressor
Author: Neuralmagic, Inc.
Author-email: support@neuralmagic.com
License: Apache
Keywords: llmcompressor,llms,large language models,transformers,pytorch,huggingface,compressors,compression,quantization,pruning,sparsity,optimization,model optimization,model compression,
Classifier: Development Status :: 5 - Production/Stable
Classifier: Programming Language :: Python :: 3
Classifier: Programming Language :: Python :: 3 :: Only
Classifier: Intended Audience :: Developers
Classifier: Intended Audience :: Education
Classifier: Intended Audience :: Information Technology
Classifier: Intended Audience :: Science/Research
Classifier: License :: OSI Approved :: Apache Software License
Classifier: Operating System :: POSIX :: Linux
Classifier: Topic :: Scientific/Engineering
Classifier: Topic :: Scientific/Engineering :: Artificial Intelligence
Classifier: Topic :: Scientific/Engineering :: Mathematics
Classifier: Topic :: Software Development
Classifier: Topic :: Software Development :: Libraries :: Python Modules
Requires-Python: >=3.10
License-File: LICENSE
License-File: NOTICE
Requires-Dist: loguru<=0.7.3,>=0.7.2
Requires-Dist: pyyaml<=6.0.3,>=6.0.1
Requires-Dist: numpy<=2.3.5,>=2.0.0
Requires-Dist: requests<=2.32.5,>=2.32.2
Requires-Dist: tqdm<=4.67.1,>=4.66.3
Requires-Dist: torch<=2.9.1,>=2.7.0
Requires-Dist: transformers<=4.57.3,>=4.54.0
Requires-Dist: datasets<=4.4.1,>=4.0.0
Requires-Dist: accelerate<=1.12.0,>=1.6.0
Requires-Dist: nvidia-ml-py<=13.590.44,>=12.560.30
Requires-Dist: pillow<=12.0.0,>=10.4.0
Requires-Dist: compressed-tensors==0.13.0
Provides-Extra: dev
Requires-Dist: pytest>=6.0.0; extra == "dev"
Requires-Dist: pytest-mock>=3.6.0; extra == "dev"
Requires-Dist: pytest-rerunfailures>=13.0; extra == "dev"
Requires-Dist: lm_eval==0.4.9.2; extra == "dev"
Requires-Dist: beautifulsoup4~=4.12.3; extra == "dev"
Requires-Dist: cmarkgfm>=2024.1.14; extra == "dev"
Requires-Dist: trl>=0.10.1; extra == "dev"
Requires-Dist: pandas<2.3.0; extra == "dev"
Requires-Dist: torchvision; extra == "dev"
Requires-Dist: librosa==0.11.0; extra == "dev"
Requires-Dist: soundfile; extra == "dev"
Requires-Dist: torchcodec; extra == "dev"
Requires-Dist: mypy~=1.10.0; extra == "dev"
Requires-Dist: ruff~=0.4.8; extra == "dev"
Requires-Dist: pre-commit; extra == "dev"
Requires-Dist: mkdocs; extra == "dev"
Requires-Dist: mkdocs-material[imaging]; extra == "dev"
Requires-Dist: markdown; extra == "dev"
Requires-Dist: pymdown-extensions; extra == "dev"
Requires-Dist: mkdocs-section-index; extra == "dev"
Requires-Dist: mkdocs-minify-plugin; extra == "dev"
Requires-Dist: mkdocs-api-autonav; extra == "dev"
Requires-Dist: mkdocstrings-python; extra == "dev"
Requires-Dist: mkdocs-gen-files; extra == "dev"
Requires-Dist: mkdocs-nav-weight; extra == "dev"
Provides-Extra: autoround
Requires-Dist: auto-round==0.9.2; extra == "autoround"
Dynamic: author
Dynamic: author-email
Dynamic: classifier
Dynamic: description
Dynamic: description-content-type
Dynamic: home-page
Dynamic: keywords
Dynamic: license
Dynamic: license-file
Dynamic: provides-extra
Dynamic: requires-dist
Dynamic: requires-python
Dynamic: summary
